{
    "weights": [
        {
            "id": 1,
            "date": 1734369737415,
            "weight": 99.0,
            "weight_units": "kg"
        },
        {
            "id": 2,
            "date": 1734542537415,
            "weight": 98.5,
            "weight_units": "kg"
        },
        {
            "id": 3,
            "date": 1734888137415,
            "weight": 98.1,
            "weight_units": "kg"
        },
        {
            "id": 4,
            "date": 1735233737415,
            "weight": 98.2,
            "weight_units": "kg"
        },
        {
            "id": 5,
            "date": 1735406537415,
            "weight": 97.9,
            "weight_units": "kg"
        },
        {
            "id": 6,
            "date": 1735579337415,
            "weight": 97.7,
            "weight_units": "kg"
        },
        {
            "id": 7,
            "date": 1735924937415,
            "weight": 97.3,
            "weight_units": "kg"
        },
        {
            "id": 8,
            "date": 1736184137415,
            "weight": 96.8,
            "weight_units": "kg"
        },
        {
            "id": 9,
            "date": 1736529737415,
            "weight": 96.8,
            "weight_units": "kg"
        },
        {
            "id": 10,
            "date": 1736875337415,
            "weight": 96.8,
            "weight_units": "kg"
        },
        {
            "id": 11,
            "date": 1737220937415,
            "weight": 96.5,
            "weight_units": "kg"
        },
        {
            "id": 12,
            "date": 1737566537415,
            "weight": 96.8,
            "weight_units": "kg"
        },
        {
            "id": 13,
            "date": 1737739337415,
            "weight": 96.5,
            "weight_units": "kg"
        },
        {
            "id": 14,
            "date": 1738084937415,
            "weight": 96.5,
            "weight_units": "kg"
        },
        {
            "id": 15,
            "date": 1738344137415,
            "weight": 96.1,
            "weight_units": "kg"
        },
        {
            "id": 16,
            "date": 1738516937415,
            "weight": 95.8,
            "weight_units": "kg"
        },
        {
            "id": 17,
            "date": 1738776137415,
            "weight": 95.4,
            "weight_units": "kg"
        },
        {
            "id": 18,
            "date": 1739035337415,
            "weight": 95.0,
            "weight_units": "kg"
        },
        {
            "id": 19,
            "date": 1739294537415,
            "weight": 95.0,
            "weight_units": "kg"
        },
        {
            "id": 20,
            "date": 1739553737415,
            "weight": 95.1,
            "weight_units": "kg"
        },
        {
            "id": 21,
            "date": 1739726537415,
            "weight": 95.0,
            "weight_units": "kg"
        },
        {
            "id": 22,
            "date": 1739899337415,
            "weight": 94.8,
            "weight_units": "kg"
        },
        {
            "id": 23,
            "date": 1740158537415,
            "weight": 94.8,
            "weight_units": "kg"
        },
        {
            "id": 24,
            "date": 1740417737415,
            "weight": 94.5,
            "weight_units": "kg"
        },
        {
            "id": 25,
            "date": 1740590537415,
            "weight": 94.8,
            "weight_units": "kg"
        },
        {
            "id": 26,
            "date": 1740763337415,
            "weight": 94.4,
            "weight_units": "kg"
        },
        {
            "id": 27,
            "date": 1740936137415,
            "weight": 94.2,
            "weight_units": "kg"
        },
        {
            "id": 28,
            "date": 1741281737415,
            "weight": 93.9,
            "weight_units": "kg"
        },
        {
            "id": 29,
            "date": 1741627337415,
            "weight": 93.8,
            "weight_units": "kg"
        },
        {
            "id": 30,
            "date": 1741972937415,
            "weight": 93.5,
            "weight_units": "kg"
        },
        {
            "id": 31,
            "date": 1742232137415,
            "weight": 93.5,
            "weight_units": "kg"
        },
        {
            "id": 32,
            "date": 1742577737415,
            "weight": 93.1,
            "weight_units": "kg"
        },
        {
            "id": 33,
            "date": 1742836937415,
            "weight": 93.1,
            "weight_units": "kg"
        },
        {
            "id": 34,
            "date": 1743096137415,
            "weight": 93.1,
            "weight_units": "kg"
        },
        {
            "id": 35,
            "date": 1743441737415,
            "weight": 92.8,
            "weight_units": "kg"
        },
        {
            "id": 36,
            "date": 1743700937415,
            "weight": 92.5,
            "weight_units": "kg"
        },
        {
            "id": 37,
            "date": 1744046537415,
            "weight": 92.4,
            "weight_units": "kg"
        },
        {
            "id": 38,
            "date": 1744392137415,
            "weight": 92.3,
            "weight_units": "kg"
        },
        {
            "id": 39,
            "date": 1744564937415,
            "weight": 92.1,
            "weight_units": "kg"
        },
        {
            "id": 40,
            "date": 1744910537415,
            "weight": 91.7,
            "weight_units": "kg"
        },
        {
            "id": 41,
            "date": 1745083337415,
            "weight": 91.3,
            "weight_units": "kg"
        },
        {
            "id": 42,
            "date": 1745428937415,
            "weight": 91.0,
            "weight_units": "kg"
        },
        {
            "id": 43,
            "date": 1745774537415,
            "weight": 90.9,
            "weight_units": "kg"
        },
        {
            "id": 44,
            "date": 1745947337415,
            "weight": 90.5,
            "weight_units": "kg"
        },
        {
            "id": 45,
            "date": 1746120137415,
            "weight": 90.2,
            "weight_units": "kg"
        },
        {
            "id": 46,
            "date": 1746465737415,
            "weight": 89.8,
            "weight_units": "kg"
        },
        {
            "id": 47,
            "date": 1746724937415,
            "weight": 89.6,
            "weight_units": "kg"
        },
        {
            "id": 48,
            "date": 1746897737415,
            "weight": 89.7,
            "weight_units": "kg"
        },
        {
            "id": 49,
            "date": 1747156937415,
            "weight": 89.6,
            "weight_units": "kg"
        },
        {
            "id": 50,
            "date": 1747416137415,
            "weight": 89.1,
            "weight_units": "kg"
        }
    ],
    "goal": {
        "date": 1762968137415,
        "weight": 85.0,
        "weight_units": "kg"
    }
}
